libcli/__init__.py
libcli/actions/__init__.py
libcli/actions/base.py
libcli/actions/basehelp.py
libcli/actions/longhelp.py
libcli/actions/longmarkdown.py
libcli/actions/markdown.py
libcli/basecli.py
libcli/basecmd.py
libcli/formatters/color.py
libcli/formatters/markdown.py
libcli/options/__init__.py
libcli/options/base.py
libcli/options/completion.py
libcli/options/printconfig.py
libcli/options/printurl.py
libcli/py.typed
rlane_libcli-1.0.8.dist-info/METADATA
rlane_libcli-1.0.8.dist-info/WHEEL
rlane_libcli-1.0.8.dist-info/entry_points.txt
rlane_libcli-1.0.8.dist-info/licenses/LICENSE
rlane_libcli-1.0.8.dist-info/RECORD
