Metadata-Version: 2.1
Name: rlane-libcli
Version: 1.0.8
Summary: Command line interface framework
Keywords: argparse,cli,color,markdown,python
Author-Email: Russel Lane <russel@rlane.com>
License: MIT
Classifier: Development Status :: 4 - Beta
Classifier: Intended Audience :: Developers
Classifier: License :: OSI Approved :: MIT License
Classifier: Programming Language :: Python :: 3
Classifier: Topic :: Software Development :: Libraries :: Python Modules
Project-URL: Homepage, https://github.com/russellane/libcli
Requires-Python: >=3.10
Requires-Dist: ansicolors>=1.1.8
Requires-Dist: argcomplete>=3.5.1
Requires-Dist: tomli>=2.1.0
